face_classify/__init__.py
face_classify/classifier.py
face_classify/eye_class.py
face_classify/face_class.py
face_classify/general_lib.py
face_classify/group_picture_class.py
face_classify/image_class.py
face_classify/model_lib.py
face_classify/model/model_blurry.json
face_classify/model/model_blurry_weights.h5
face_classify/model/model_eye.json
face_classify/model/model_eye_weights.h5
face_classify/model/model_profile.json
face_classify/model/model_profile_weights.h5
face_classify/model/model_sunglasses.json
face_classify/model/model_sunglasses_weights.h5
face_classify-0.0.9.dist-info/METADATA
face_classify-0.0.9.dist-info/WHEEL
face_classify-0.0.9.dist-info/top_level.txt
face_classify-0.0.9.dist-info/RECORD
