Metadata-Version: 2.1
Name: face-classify
Version: 0.0.9
Summary: This repository is used for face classification.
Home-page: https://github.com/jordi-zaragoza
Author: Jordi Zaragoza
Author-email: j.z.cuffi@gmail.com
License: MIT
Requires-Dist: matplotlib (>=3.0)
Requires-Dist: numpy (>=1.8)
Requires-Dist: tensorflow (>=2.6)
Requires-Dist: face-recognition (>=1.3.0)
